dtouch/__init__.py
dtouch/__main__.py
dtouch/py.typed
dtouch-0.1.1.dev1.dist-info/WHEEL
dtouch-0.1.1.dev1.dist-info/entry_points.txt
dtouch-0.1.1.dev1.dist-info/METADATA
dtouch-0.1.1.dev1.dist-info/RECORD
