Metadata-Version: 2.3
Name: dtouch
Version: 0.1.1.dev1
Summary: Add your description here
Author: dyotak
Author-email: dyotak <dyotak10@gmail.com>
Requires-Dist: argparse>=1.4.0
Requires-Dist: pathlib>=1.0.1
Requires-Python: >=3.10
